Metadata-Version: 1.0
Name: qcp
Version: 0.9.2
Summary: quick scp in isomorphic enviroments
Home-page: https://gitee.com/zzqq2199/qcp
Author: togo
Author-email: zhouquanjs@qq.com
License: MIT
Platform: UNKNOWN
